Desigz/__init__.py
Desigz/Material/ICO.ico
Desigz/message.py
Desigz/system.pyw
Desigz/window.py
desigz-1.0.0.dist-info/WHEEL
desigz-1.0.0.dist-info/METADATA
desigz-1.0.0.dist-info/RECORD
