Metadata-Version: 2.1
Name: desigz
Version: 1.0.0
Summary: Modern Graphic Library
Author: 6IXK1LL
Author-email: jxpkaxyz@gmail.com
Requires-Python: ==3.9.2
Classifier: Programming Language :: Python :: 3
